yamcs/clientversion.py
yamcs/model.py
yamcs/api/annotations_pb2.py
yamcs/api/exception_pb2.py
yamcs/api/httpbody_pb2.py
yamcs/api/websocket_pb2.py
yamcs/archive/__init__.py
yamcs/archive/client.py
yamcs/archive/model.py
yamcs/client/__init__.py
yamcs/client/activities.py
yamcs/client/clientversion.py
yamcs/client/model.py
yamcs/client/archive/__init__.py
yamcs/client/archive/client.py
yamcs/client/archive/model.py
yamcs/client/core/__init__.py
yamcs/client/core/auth.py
yamcs/client/core/context.py
yamcs/client/core/exceptions.py
yamcs/client/core/futures.py
yamcs/client/core/helpers.py
yamcs/client/core/pagination.py
yamcs/client/core/subscriptions.py
yamcs/client/filetransfer/__init__.py
yamcs/client/filetransfer/client.py
yamcs/client/filetransfer/model.py
yamcs/client/links/__init__.py
yamcs/client/links/client.py
yamcs/client/links/model.py
yamcs/client/mdb/__init__.py
yamcs/client/mdb/client.py
yamcs/client/mdb/model.py
yamcs/client/storage/__init__.py
yamcs/client/storage/client.py
yamcs/client/storage/model.py
yamcs/client/tco/__init__.py
yamcs/client/tco/client.py
yamcs/client/tco/model.py
yamcs/client/timeline/__init__.py
yamcs/client/timeline/client.py
yamcs/client/timeline/model.py
yamcs/client/tmtc/__init__.py
yamcs/client/tmtc/client.py
yamcs/client/tmtc/model.py
yamcs/core/__init__.py
yamcs/core/auth.py
yamcs/core/context.py
yamcs/core/exceptions.py
yamcs/core/futures.py
yamcs/core/helpers.py
yamcs/core/pagination.py
yamcs/core/subscriptions.py
yamcs/filetransfer/__init__.py
yamcs/filetransfer/client.py
yamcs/filetransfer/model.py
yamcs/link/__init__.py
yamcs/link/client.py
yamcs/link/model.py
yamcs/mdb/__init__.py
yamcs/mdb/client.py
yamcs/mdb/model.py
yamcs/protobuf/yamcs_pb2.py
yamcs/protobuf/actions/actions_pb2.py
yamcs/protobuf/activities/activities_pb2.py
yamcs/protobuf/activities/activities_service_pb2.py
yamcs/protobuf/alarms/alarms_pb2.py
yamcs/protobuf/alarms/alarms_service_pb2.py
yamcs/protobuf/archive/archive_pb2.py
yamcs_client-1.12.1.dist-info/licenses/LICENSE
yamcs_client-1.12.1.dist-info/METADATA
yamcs_client-1.12.1.dist-info/WHEEL
yamcs_client-1.12.1.dist-info/top_level.txt
yamcs_client-1.12.1.dist-info/RECORD
